LiyongPythonJinxingShujufenxiDi2BanFix1/README.md
LiyongPythonJinxingShujufenxiDi2BanFix1/__init__.py
LiyongPythonJinxingShujufenxiDi2BanFix1/__main__.py
LiyongPythonJinxingShujufenxiDi2BanFix1/file.epub
LiyongPythonJinxingShujufenxiDi2BanFix1/index.html
LiyongPythonJinxingShujufenxiDi2BanFix1/css/__init__.py
LiyongPythonJinxingShujufenxiDi2BanFix1/css/annotations.css
LiyongPythonJinxingShujufenxiDi2BanFix1/css/main.css
LiyongPythonJinxingShujufenxiDi2BanFix1/css/normalize.css
LiyongPythonJinxingShujufenxiDi2BanFix1/css/popup.css
LiyongPythonJinxingShujufenxiDi2BanFix1/font/__init__.py
LiyongPythonJinxingShujufenxiDi2BanFix1/font/fontello.eot
LiyongPythonJinxingShujufenxiDi2BanFix1/font/fontello.svg
LiyongPythonJinxingShujufenxiDi2BanFix1/font/fontello.ttf
LiyongPythonJinxingShujufenxiDi2BanFix1/font/fontello.woff
LiyongPythonJinxingShujufenxiDi2BanFix1/img/__init__.py
LiyongPythonJinxingShujufenxiDi2BanFix1/img/annotator-glyph-sprite.png
LiyongPythonJinxingShujufenxiDi2BanFix1/img/annotator-icon-sprite.png
LiyongPythonJinxingShujufenxiDi2BanFix1/img/apple-touch-icon.png
LiyongPythonJinxingShujufenxiDi2BanFix1/img/cancelfullscreen.png
LiyongPythonJinxingShujufenxiDi2BanFix1/img/close.png
LiyongPythonJinxingShujufenxiDi2BanFix1/img/fullscreen.png
LiyongPythonJinxingShujufenxiDi2BanFix1/img/loader.gif
LiyongPythonJinxingShujufenxiDi2BanFix1/img/menu-icon.png
LiyongPythonJinxingShujufenxiDi2BanFix1/img/save.png
LiyongPythonJinxingShujufenxiDi2BanFix1/img/saved.png
LiyongPythonJinxingShujufenxiDi2BanFix1/img/settings-s.png
LiyongPythonJinxingShujufenxiDi2BanFix1/img/settings.png
LiyongPythonJinxingShujufenxiDi2BanFix1/img/star.png
LiyongPythonJinxingShujufenxiDi2BanFix1/js/__init__.py
LiyongPythonJinxingShujufenxiDi2BanFix1/js/epub.js
LiyongPythonJinxingShujufenxiDi2BanFix1/js/epub.min.js
LiyongPythonJinxingShujufenxiDi2BanFix1/js/epub.min.map
LiyongPythonJinxingShujufenxiDi2BanFix1/js/hooks.min.js
LiyongPythonJinxingShujufenxiDi2BanFix1/js/hooks.min.map
liyong_python_jinxing_shujufenxi_di_2_ban_fix1-2024.3.6.0.dist-info/METADATA
liyong_python_jinxing_shujufenxi_di_2_ban_fix1-2024.3.6.0.dist-info/WHEEL
liyong_python_jinxing_shujufenxi_di_2_ban_fix1-2024.3.6.0.dist-info/entry_points.txt
liyong_python_jinxing_shujufenxi_di_2_ban_fix1-2024.3.6.0.dist-info/top_level.txt
liyong_python_jinxing_shujufenxi_di_2_ban_fix1-2024.3.6.0.dist-info/RECORD
